bloomlib-0.0.3.dist-info/METADATA
bloomlib-0.0.3.dist-info/WHEEL
bloomlib-0.0.3.dist-info/licenses/LICENSE.txt
bloomlib/__init__.py
bloomlib/__init__.pyi
bloomlib/py.typed
bloomlib/bloomlib.cpython-39-x86_64-linux-gnu.so
bloomlib-0.0.3.dist-info/RECORD
