Metadata-Version: 2.3
Name: bloomlib
Version: 0.0.3
Classifier: Programming Language :: Rust
Classifier: Programming Language :: Python :: 3
Classifier: Programming Language :: Python :: Implementation :: CPython
Classifier: Development Status :: 3 - Alpha
Classifier: Intended Audience :: Developers
Classifier: License :: OSI Approved :: MIT License
License-File: LICENSE.txt
Summary: Library that offers all types of Bloom filters, implemented in Rust
Home-Page: https://www.mikehuls.com
Author: Mike Huls
Author-email: mikehuls42@gmail.com
License: MIT
Requires-Python: >=3.9
Project-URL: Homepage, https://github.com/mike-huls/bloomlib
Project-URL: Bug Tracker, https://github.com/mike-huls/bloomlib/issues
Project-URL: Documentation, https://github.com/mike-huls/bloomlib/blob/master/README.md/
Project-URL: Source, https://github.com/mike-huls/bloomlib/
Project-URL: Say Thanks!, https://www.buymeacoffee.com/mikehuls
